pyrad/__init__.py
pyrad/cameras/__init__.py
pyrad/cameras/camera_paths.py
pyrad/cameras/cameras.py
pyrad/cameras/rays.py
pyrad/cameras/utils.py
pyrad/cuda/__init__.py
pyrad/cuda/sampler.py
pyrad/data/__init__.py
pyrad/data/colmap_utils.py
pyrad/data/dataloader.py
pyrad/data/image_dataset.py
pyrad/data/image_sampler.py
pyrad/data/pixel_sampler.py
pyrad/data/structs.py
pyrad/data/utils.py
pyrad/data/format/__init__.py
pyrad/data/format/blender.py
pyrad/data/format/friends.py
pyrad/data/format/instant_ngp.py
pyrad/data/format/llff.py
pyrad/data/format/mipnerf_360.py
pyrad/engine/__init__.py
pyrad/engine/base.py
pyrad/engine/trainer.py
pyrad/fields/__init__.py
pyrad/fields/base.py
pyrad/fields/instant_ngp_field.py
pyrad/fields/nerf_field.py
pyrad/fields/nerfw_field.py
pyrad/fields/modules/__init__.py
pyrad/fields/modules/base.py
pyrad/fields/modules/embedding.py
pyrad/fields/modules/encoding.py
pyrad/fields/modules/field_heads.py
pyrad/fields/modules/field_losses.py
pyrad/fields/modules/mlp.py
pyrad/fields/modules/spatial_distortions.py
pyrad/graphs/__init__.py
pyrad/graphs/base.py
pyrad/graphs/instant_ngp.py
pyrad/graphs/mipnerf.py
pyrad/graphs/mipnerf_360.py
pyrad/graphs/nerfw.py
pyrad/graphs/semantic_nerf.py
pyrad/graphs/tensorf.py
pyrad/graphs/vanilla_nerf.py
pyrad/graphs/modules/__init__.py
pyrad/graphs/modules/ray_generator.py
pyrad/graphs/modules/ray_losses.py
pyrad/graphs/modules/ray_sampler.py
pyrad/graphs/modules/scene_colliders.py
pyrad/optimizers/__init__.py
pyrad/optimizers/loss.py
pyrad/optimizers/optimizers.py
pyrad/renderers/__init__.py
pyrad/renderers/base.py
pyrad/renderers/renderers.py
pyrad/utils/__init__.py
pyrad/utils/activations.py
pyrad/utils/callbacks.py
pyrad/utils/colors.py
pyrad/utils/comms.py
pyrad/utils/config.py
pyrad/utils/decorators.py
pyrad/utils/io.py
pyrad/utils/math.py
pyrad/utils/misc.py
pyrad/utils/plotly.py
pyrad/utils/profiler.py
pyrad/utils/tensor_dataclass.py
pyrad/utils/visualization.py
pyrad/utils/writer.py
nerfactory-0.0.0.dist-info/LICENSE
nerfactory-0.0.0.dist-info/METADATA
nerfactory-0.0.0.dist-info/WHEEL
nerfactory-0.0.0.dist-info/top_level.txt
nerfactory-0.0.0.dist-info/RECORD
