Metadata-Version: 2.1
Name: nerfactory
Version: 0.0.0
Summary: All-in-one repository for state-of-the-art NeRFs
License: Apache 2.0
Project-URL: Documentation, https://plenoptix-pyrad.readthedocs-hosted.com/en/latest/?badge=latest
Classifier: Development Status :: 3 - Alpha
Classifier: Programming Language :: Python
Requires-Python: >=3.7
License-File: LICENSE
